README.rst
setup.py
rethinkstuff/__init__.py
rethinkstuff.egg-info/PKG-INFO
rethinkstuff.egg-info/SOURCES.txt
rethinkstuff.egg-info/dependency_links.txt
rethinkstuff.egg-info/requires.txt
rethinkstuff.egg-info/top_level.txt