Metadata-Version: 1.1
Name: rethinkstuff
Version: 0.1.7
Summary: Rudimentary rethinkdb python library with some smarts, perhaps some dumbs
Home-page: https://github.com/nlevitt/rethinkstuff
Author: Noah Levitt
Author-email: nlevitt@archive.org
License: UNKNOWN
Platform: UNKNOWN
Classifier: Programming Language :: Python :: 2.7
Classifier: Programming Language :: Python :: 3.4
Classifier: Programming Language :: Python :: 3.5
